odoo/addons/purchase_order_product_recommendation/README.rst
odoo/addons/purchase_order_product_recommendation/__init__.py
odoo/addons/purchase_order_product_recommendation/__manifest__.py
odoo/addons/purchase_order_product_recommendation/i18n/es.po
odoo/addons/purchase_order_product_recommendation/i18n/it.po
odoo/addons/purchase_order_product_recommendation/i18n/pt_BR.po
odoo/addons/purchase_order_product_recommendation/i18n/purchase_order_product_recommendation.pot
odoo/addons/purchase_order_product_recommendation/readme/CONTRIBUTORS.md
odoo/addons/purchase_order_product_recommendation/readme/DESCRIPTION.md
odoo/addons/purchase_order_product_recommendation/readme/USAGE.md
odoo/addons/purchase_order_product_recommendation/security/ir.model.access.csv
odoo/addons/purchase_order_product_recommendation/static/description/icon.png
odoo/addons/purchase_order_product_recommendation/static/description/index.html
odoo/addons/purchase_order_product_recommendation/tests/__init__.py
odoo/addons/purchase_order_product_recommendation/tests/test_recommendation.py
odoo/addons/purchase_order_product_recommendation/views/purchase_order_view.xml
odoo/addons/purchase_order_product_recommendation/wizards/__init__.py
odoo/addons/purchase_order_product_recommendation/wizards/purchase_order_recommendation.py
odoo/addons/purchase_order_product_recommendation/wizards/purchase_order_recommendation_view.xml
odoo_addon_purchase_order_product_recommendation-18.0.1.0.0.4.dist-info/METADATA
odoo_addon_purchase_order_product_recommendation-18.0.1.0.0.4.dist-info/WHEEL
odoo_addon_purchase_order_product_recommendation-18.0.1.0.0.4.dist-info/top_level.txt
odoo_addon_purchase_order_product_recommendation-18.0.1.0.0.4.dist-info/RECORD
